Landsifier/Landsifier_DataPreparation.py
Landsifier/Landsifier_ML_Training.py
Landsifier/Landsifier_Prediction.py
Landsifier/Landsifier_Visualization.py
Landsifier/__init__.py
Landsifier/utility.py
landsifier-2.0.5.dist-info/licenses/LICENSE.txt
landsifier-2.0.5.dist-info/METADATA
landsifier-2.0.5.dist-info/WHEEL
landsifier-2.0.5.dist-info/top_level.txt
landsifier-2.0.5.dist-info/RECORD
